{
    "html_attributions": [],
    "results": [
        {
            "business_status": "OPERATIONAL",
            "formatted_address": "21 Choa Chu Kang Avenue 4 #04-01/02 and #05-06, Lot One Shopper\u2019s Mall, 689812",
            "geometry": {
                "location": {
                    "lat": 1.3850239,
                    "lng": 103.7451634
                },
                "viewport": {
                    "northeast": {
                        "lat": 1.386311879892722,
                        "lng": 103.7465342298927
                    },
                    "southwest": {
                        "lat": 1.383612220107278,
                        "lng": 103.7438345701073
                    }
                }
            },
            "icon": "https://maps.gstatic.com/mapfiles/place_api/icons/v1/png_71/school-71.png",
            "icon_background_color": "#7B9EB0",
            "icon_mask_base_uri": "https://maps.gstatic.com/mapfiles/place_api/icons/v2/school_pinlet",
            "name": "Choa Chu Kang Public Library",
            "opening_hours": {
                "open_now": true
            },
            "photos": [
                {
                    "height": 2268,
                    "html_attributions": [
                        "<a href=\"https://maps.google.com/maps/contrib/114763821595401889761\">Rudy Tjong</a>"
                    ],
                    "photo_reference": "Aap_uEB13zMTQIW02KtapujA4C7S0uLy5wF4jlefbcpL0P6g7nqIdi8dAgzDq7f6FU4rZ9UvOJSNqD2pExNOq5MFsti6M-12vFzj6ZRDTPHSYYKNuEuyXtG8GIjSVwaO_v4hnPM8Pr30doYjMS_E4oJDyuC34--5-GD_b8I_dtk2-m9ugpmU",
                    "width": 4032
                }
            ],
            "place_id": "ChIJ5-Dtl-kR2jERllI9-1NpYVY",
            "plus_code": {
                "compound_code": "9PPW+23 Singapore",
                "global_code": "6PH59PPW+23"
            },
            "rating": 4.4,
            "reference": "ChIJ5-Dtl-kR2jERllI9-1NpYVY",
            "types": [
                "library",
                "point_of_interest",
                "establishment"
            ],
            "user_ratings_total": 98
        },
        {
            "business_status": "OPERATIONAL",
            "formatted_address": "1 Jelebu Road #04-04 & 16/17 Bukit Panjang Plaza, 677743",
            "geometry": {
                "location": {
                    "lat": 1.3795982,
                    "lng": 103.7645426
                },
                "viewport": {
                    "northeast": {
                        "lat": 1.380816379892722,
                        "lng": 103.7660216798927
                    },
                    "southwest": {
                        "lat": 1.378116720107278,
                        "lng": 103.7633220201073
                    }
                }
            },
            "icon": "https://maps.gstatic.com/mapfiles/place_api/icons/v1/png_71/school-71.png",
            "icon_background_color": "#7B9EB0",
            "icon_mask_base_uri": "https://maps.gstatic.com/mapfiles/place_api/icons/v2/school_pinlet",
            "name": "Bukit Panjang Public Library",
            "opening_hours": {
                "open_now": true
            },
            "photos": [
                {
                    "height": 1458,
                    "html_attributions": [
                        "<a href=\"https://maps.google.com/maps/contrib/105863133358477079886\">Xoom Too</a>"
                    ],
                    "photo_reference": "Aap_uECxaMBlFf70ESFp5EJi4VZJlhWfcwFJ1Mfbfy2q4ct2JZKrfp_bZzspscu57skQKbUQ2ULpuTVLSDjFB7naz5jspNZQPJZJn9d_SRumyNUCUBGER_1o-2AvqB1FDB6lrblFWjYR2_JHKBFFsU-01k9bYSbPw5vw3ZXzziq7pHiOfrGN",
                    "width": 2592
                }
            ],
            "place_id": "ChIJAQAASKMR2jER1rsyt_ipOM0",
            "plus_code": {
                "compound_code": "9QH7+RR Singapore",
                "global_code": "6PH59QH7+RR"
            },
            "rating": 4.3,
            "reference": "ChIJAQAASKMR2jER1rsyt_ipOM0",
            "types": [
                "library",
                "point_of_interest",
                "establishment"
            ],
            "user_ratings_total": 159
        }
    ],
    "status": "OK"
}